opentelemetry/instrumentation/bootstrap.py
opentelemetry/instrumentation/bootstrap_gen.py
opentelemetry/instrumentation/dependencies.py
opentelemetry/instrumentation/distro.py
opentelemetry/instrumentation/environment_variables.py
opentelemetry/instrumentation/instrumentor.py
opentelemetry/instrumentation/propagators.py
opentelemetry/instrumentation/py.typed
opentelemetry/instrumentation/utils.py
opentelemetry/instrumentation/version.py
opentelemetry/instrumentation/auto_instrumentation/__init__.py
opentelemetry/instrumentation/auto_instrumentation/sitecustomize.py
opentelemetry_instrumentation-0.33b0.dist-info/LICENSE
opentelemetry_instrumentation-0.33b0.dist-info/METADATA
opentelemetry_instrumentation-0.33b0.dist-info/WHEEL
opentelemetry_instrumentation-0.33b0.dist-info/entry_points.txt
opentelemetry_instrumentation-0.33b0.dist-info/top_level.txt
opentelemetry_instrumentation-0.33b0.dist-info/RECORD
