Metadata-Version: 2.1
Name: opentelemetry-instrumentation
Version: 0.33b0
Summary: Instrumentation Tools & Auto Instrumentation for OpenTelemetry Python
Home-page: https://github.com/open-telemetry/opentelemetry-python/tree/main/opentelemetry-instrumentation
Author: OpenTelemetry Authors
Author-email: cncf-opentelemetry-contributors@lists.cncf.io
License: Apache-2.0
Platform: any
Classifier: Development Status :: 4 - Beta
Classifier: Intended Audience :: Developers
Classifier: License :: OSI Approved :: Apache Software License
Classifier: Programming Language :: Python
Classifier: Programming Language :: Python :: 3
Classifier: Programming Language :: Python :: 3.6
Classifier: Programming Language :: Python :: 3.7
Classifier: Programming Language :: Python :: 3.8
Classifier: Programming Language :: Python :: 3.9
Classifier: Programming Language :: Python :: 3.10
Requires-Python: >=3.6
License-File: LICENSE
Requires-Dist: opentelemetry-api (~=1.4)
Requires-Dist: setuptools (>=16.0)
Requires-Dist: wrapt (<2.0.0,>=1.0.0)
Provides-Extra: test
